<Bills>
  <Bill>
    <Id>13583805</Id>
    <NumberCode>C-239</NumberCode>
    <NumberPrefix>C</NumberPrefix>
    <Number>239</Number>
    <LongTitleEn>An Act to amend the Canada Health Act (accountability)</LongTitleEn>
    <LongTitleFr>Loi modifiant la Loi canadienne sur la santé (reddition de comptes)</LongTitleFr>
    <LongTitle>An Act to amend the Canada Health Act (accountability)</LongTitle>
    <ShortTitleEn>
    </ShortTitleEn>
    <ShortTitleFr>
    </ShortTitleFr>
    <ShortTitle>
    </ShortTitle>
    <StatusId>349</StatusId>
    <StatusNameEn>At second reading in the House of Commons</StatusNameEn>
    <StatusNameFr>À la deuxième lecture à la Chambre des communes</StatusNameFr>
    <StatusName>At second reading in the House of Commons</StatusName>
    <LatestCompletedMajorStageId>60043</LatestCompletedMajorStageId>
    <LatestCompletedMajorStageNameEn>First reading</LatestCompletedMajorStageNameEn>
    <LatestCompletedMajorStageNameFr>Première lecture</LatestCompletedMajorStageNameFr>
    <LatestCompletedMajorStageName>First reading</LatestCompletedMajorStageName>
    <LatestCompletedMajorStageNameWithChamberSuffix>First reading in the House of Commons</LatestCompletedMajorStageNameWithChamberSuffix>
    <IsInSenatePreStudy>false</IsInSenatePreStudy>
    <LatestCompletedMajorStageChamberOrganizationId>1</LatestCompletedMajorStageChamberOrganizationId>
    <LatestCompletedMajorStageChamberNameEn>House of Commons</LatestCompletedMajorStageChamberNameEn>
    <LatestCompletedMajorStageChamberNameFr>Chambre des communes</LatestCompletedMajorStageChamberNameFr>
    <LatestCompletedMajorStageChamberName>House of Commons</LatestCompletedMajorStageChamberName>
    <OngoingStageId>60030</OngoingStageId>
    <OngoingStageNameEn>Second reading</OngoingStageNameEn>
    <OngoingStageNameFr>Deuxième lecture</OngoingStageNameFr>
    <OngoingStageName>Second reading</OngoingStageName>
    <LatestCompletedBillStageId>60029</LatestCompletedBillStageId>
    <LatestCompletedBillStageNameEn>First reading</LatestCompletedBillStageNameEn>
    <LatestCompletedBillStageNameFr>Première lecture</LatestCompletedBillStageNameFr>
    <LatestCompletedBillStageName>First reading</LatestCompletedBillStageName>
    <LatestCompletedBillStageChamberOrganizationId>1</LatestCompletedBillStageChamberOrganizationId>
    <LatestCompletedBillStageChamberNameEn>House of Commons</LatestCompletedBillStageChamberNameEn>
    <LatestCompletedBillStageChamberNameFr>Chambre des communes</LatestCompletedBillStageChamberNameFr>
    <LatestCompletedBillStageChamberName>House of Commons</LatestCompletedBillStageChamberName>
    <LatestCompletedBillStageDateTime>2025-09-22T15:48:34.91</LatestCompletedBillStageDateTime>
    <ParliamentNumber>45</ParliamentNumber>
    <SessionNumber>1</SessionNumber>
    <BillDocumentTypeId>4</BillDocumentTypeId>
    <BillDocumentTypeNameEn>Private Member’s Bill</BillDocumentTypeNameEn>
    <BillDocumentTypeNameFr>Projet de loi émanant d'un député</BillDocumentTypeNameFr>
    <BillDocumentTypeName>Private Member’s Bill</BillDocumentTypeName>
    <IsGovernmentBill>false</IsGovernmentBill>
    <OriginatingChamberOrganizationId>1</OriginatingChamberOrganizationId>
    <OriginatingChamberNameEn>House of Commons</OriginatingChamberNameEn>
    <OriginatingChamberNameFr>Chambre des communes</OriginatingChamberNameFr>
    <OriginatingChamberName>House of Commons</OriginatingChamberName>
    <IsHouseBill>true</IsHouseBill>
    <IsSenateBill>false</IsSenateBill>
    <SponsorSenateSystemAffiliationId />
    <SponsorPersonId>31098</SponsorPersonId>
    <SponsorPersonOfficialFirstName>Sukh</SponsorPersonOfficialFirstName>
    <SponsorPersonOfficialLastName>Dhaliwal</SponsorPersonOfficialLastName>
    <SponsorPersonUsualFirstName>
    </SponsorPersonUsualFirstName>
    <SponsorPersonMiddleName>
    </SponsorPersonMiddleName>
    <SponsorPersonName>Sukh Dhaliwal</SponsorPersonName>
    <SponsorPersonShortHonorificEn>
    </SponsorPersonShortHonorificEn>
    <SponsorPersonShortHonorificFr>
    </SponsorPersonShortHonorificFr>
    <SponsorPersonShortHonorific>
    </SponsorPersonShortHonorific>
    <SponsorAffiliationTitleEn>Member of Parliament</SponsorAffiliationTitleEn>
    <SponsorAffiliationTitleFr>député</SponsorAffiliationTitleFr>
    <SponsorAffiliationTitle>Member of Parliament</SponsorAffiliationTitle>
    <SponsorAffiliationRoleId>2</SponsorAffiliationRoleId>
    <SponsorAffiliationRoleNameEn>Member of Parliament</SponsorAffiliationRoleNameEn>
    <SponsorAffiliationRoleNameFr>député(e)</SponsorAffiliationRoleNameFr>
    <SponsorAffiliationRoleName>Member of Parliament</SponsorAffiliationRoleName>
    <SponsorConstituencyId>1273</SponsorConstituencyId>
    <SponsorConstituencyNameEn>Surrey Newton</SponsorConstituencyNameEn>
    <SponsorConstituencyNameFr>Surrey Newton</SponsorConstituencyNameFr>
    <SponsorConstituencyName>Surrey Newton</SponsorConstituencyName>
    <LatestBillEventEventTypeId>60115</LatestBillEventEventTypeId>
    <LatestBillEventTypeNameEn>Debate at second reading</LatestBillEventTypeNameEn>
    <LatestBillEventTypeNameFr>Débat à l’étape de la deuxième lecture</LatestBillEventTypeNameFr>
    <LatestBillEventStageId>60030</LatestBillEventStageId>
    <LatestBillEventTypeName>Debate at second reading</LatestBillEventTypeName>
    <LatestBillEventCommitteeDetails />
    <LatestBillEventDateTime>2025-10-30T10:00:00</LatestBillEventDateTime>
    <LatestBillEventChamberOrganizationId>1</LatestBillEventChamberOrganizationId>
    <LatestBillEventChamberNameEn>House of Commons</LatestBillEventChamberNameEn>
    <LatestBillEventChamberNameFr>Chambre des communes</LatestBillEventChamberNameFr>
    <LatestBillEventChamberName>House of Commons</LatestBillEventChamberName>
    <LatestBillEventNumberOfAmendments>0</LatestBillEventNumberOfAmendments>
    <LatestBillEventAmendmentNoteId>0</LatestBillEventAmendmentNoteId>
    <LatestBillEventMeetingNumber>47</LatestBillEventMeetingNumber>
    <LatestBillEventAdditionalInformationEn>
    </LatestBillEventAdditionalInformationEn>
    <LatestBillEventAdditionalInformationFr>
    </LatestBillEventAdditionalInformationFr>
    <LatestBillEventAdditionalInformation>
    </LatestBillEventAdditionalInformation>
    <PassedHouseFirstReadingDateTime>2025-09-22T15:48:34.91</PassedHouseFirstReadingDateTime>
    <PassedHouseSecondReadingDateTime />
    <PassedHouseThirdReadingDateTime />
    <PassedSenateFirstReadingDateTime />
    <PassedSenateSecondReadingDateTime />
    <PassedSenateThirdReadingDateTime />
    <ReceivedRoyalAssentDateTime />
    <DidReinstateFromPreviousSession>false</DidReinstateFromPreviousSession>
    <ReinstatedFromBillDocumentId />
    <ReinstatedFromBillNumberCode />
    <DidReinstateInNextSession>false</DidReinstateInNextSession>
    <ReinstatedAsBillDocumentId />
    <ReinstatedAsBillNumberCode />
    <PassedFirstChamberFirstReading>true</PassedFirstChamberFirstReading>
    <PassedFirstChamberSecondReading>false</PassedFirstChamberSecondReading>
    <PassedFirstChamberThirdReading>false</PassedFirstChamberThirdReading>
    <PassedSecondChamberFirstReading>false</PassedSecondChamberFirstReading>
    <PassedSecondChamberSecondReading>false</PassedSecondChamberSecondReading>
    <PassedSecondChamberThirdReading>false</PassedSecondChamberThirdReading>
    <ReceivedRoyalAssent>false</ReceivedRoyalAssent>
    <ConsideredDuringPreviousSitting>false</ConsideredDuringPreviousSitting>
    <IsProForma>false</IsProForma>
    <BillFormId>10</BillFormId>
    <BillFormNameEn>Regular</BillFormNameEn>
    <BillFormNameFr>Ordinaire</BillFormNameFr>
    <BillFormName>Regular</BillFormName>
    <NotesEn>
    </NotesEn>
    <NotesFr>
    </NotesFr>
    <Notes>
    </Notes>
    <ShortLegislativeSummaryEn />
    <ShortLegislativeSummaryFr />
    <ShortLegislativeSummary />
    <IsFullLegislativeSummaryAvailable>false</IsFullLegislativeSummaryAvailable>
    <StatuteYear />
    <StatuteChapter />
    <BillStages>
      <BillId>0</BillId>
      <HouseBillStages>
        <BillStageId>60029</BillStageId>
        <BillStageNameEn>First reading</BillStageNameEn>
        <BillStageNameFr>Première lecture</BillStageNameFr>
        <BillStageName>First reading</BillStageName>
        <ChamberOrganizationId>1</ChamberOrganizationId>
        <ParliamentNumber>45</ParliamentNumber>
        <SessionNumber>1</SessionNumber>
        <State>4</State>
        <StateNameEn>Completed</StateNameEn>
        <StateNameFr>Terminée</StateNameFr>
        <StateAsOfDate>2025-09-22T15:48:34.91</StateAsOfDate>
        <StateName>Completed</StateName>
        <Committee />
        <Sittings>
          <NameEn>Introduction and first reading</NameEn>
          <NameFr>Dépôt et première lecture</NameFr>
          <Name>Introduction and first reading</Name>
          <Number>26</Number>
          <Date>2025-09-22T00:00:00</Date>
          <AdditionalInformationEn />
          <AdditionalInformationFr />
          <AdditionalInformation />
          <IsPublished>true</IsPublished>
        </Sittings>
        <SignificantEvents>
          <EventTypeId>60110</EventTypeId>
          <BillDocumentId>0</BillDocumentId>
          <EventNameEn>Introduction and first reading</EventNameEn>
          <EventNameFr>Dépôt et première lecture</EventNameFr>
          <EventName>Introduction and first reading</EventName>
          <EventDateTime>2025-09-22T00:00:00</EventDateTime>
          <IsCompletionOfBillStage>true</IsCompletionOfBillStage>
          <IsDefeatedEvent>false</IsDefeatedEvent>
          <CommitteeReportId />
          <CommitteeReportNumber />
          <AdditionalInformationEn>
          </AdditionalInformationEn>
          <AdditionalInformationFr>
          </AdditionalInformationFr>
          <AdditionalInformation>
          </AdditionalInformation>
          <MeetingEventId />
          <AmendmentNoteId />
        </SignificantEvents>
        <EndOfStageEvent>
          <EventTypeId>60110</EventTypeId>
          <EventTypeNameEn>Introduction and first reading</EventTypeNameEn>
          <EventTypeNameFr>Dépôt et première lecture</EventTypeNameFr>
          <EventTypeName>Introduction and first reading</EventTypeName>
          <EventStartDateTime>2025-09-22T15:48:34.91</EventStartDateTime>
          <EventEndDateTime>2025-09-22T15:48:34.91</EventEndDateTime>
        </EndOfStageEvent>
        <StageEventCount>1</StageEventCount>
        <LastStageEventStartDateTime>2025-09-22T15:48:34.91</LastStageEventStartDateTime>
        <Speeches />
        <ContainsReferralToCommitteeEvent>false</ContainsReferralToCommitteeEvent>
        <ContainsRecommittalOfBillEvent>false</ContainsRecommittalOfBillEvent>
      </HouseBillStages>
      <HouseBillStages>
        <BillStageId>60030</BillStageId>
        <BillStageNameEn>Second reading</BillStageNameEn>
        <BillStageNameFr>Deuxième lecture</BillStageNameFr>
        <BillStageName>Second reading</BillStageName>
        <ChamberOrganizationId>1</ChamberOrganizationId>
        <ParliamentNumber>45</ParliamentNumber>
        <SessionNumber>1</SessionNumber>
        <State>3</State>
        <StateNameEn>In progress</StateNameEn>
        <StateNameFr>En cours</StateNameFr>
        <StateAsOfDate />
        <StateName>In progress</StateName>
        <Committee />
        <Sittings>
          <NameEn>Debate at second reading</NameEn>
          <NameFr>Débat à l’étape de la deuxième lecture</NameFr>
          <Name>Debate at second reading</Name>
          <Number>47</Number>
          <Date>2025-10-30T00:00:00</Date>
          <AdditionalInformationEn>
          </AdditionalInformationEn>
          <AdditionalInformationFr>
          </AdditionalInformationFr>
          <AdditionalInformation>
          </AdditionalInformation>
          <IsPublished>true</IsPublished>
        </Sittings>
        <SignificantEvents>
          <EventTypeId>60112</EventTypeId>
          <BillDocumentId>0</BillDocumentId>
          <EventNameEn>Placed in the Order of Precedence</EventNameEn>
          <EventNameFr>Ajouté à l'Ordre de priorité</EventNameFr>
          <EventName>Placed in the Order of Precedence</EventName>
          <EventDateTime>2025-09-23T00:00:00</EventDateTime>
          <IsCompletionOfBillStage>false</IsCompletionOfBillStage>
          <IsDefeatedEvent>false</IsDefeatedEvent>
          <CommitteeReportId />
          <CommitteeReportNumber />
          <AdditionalInformationEn>
          </AdditionalInformationEn>
          <AdditionalInformationFr>
          </AdditionalInformationFr>
          <AdditionalInformation>
          </AdditionalInformation>
          <MeetingEventId />
          <AmendmentNoteId />
        </SignificantEvents>
        <EndOfStageEvent />
        <StageEventCount>1</StageEventCount>
        <LastStageEventStartDateTime>2025-10-30T17:30:49</LastStageEventStartDateTime>
        <Speeches>
          <BillId>0</BillId>
          <ChamberOrganizationId>1</ChamberOrganizationId>
          <InterventionEventId>13214212</InterventionEventId>
          <EventTypeId>60152</EventTypeId>
          <EventTypeNameEn>Sponsor’s speech</EventTypeNameEn>
          <EventTypeNameFr>Discours du parrain</EventTypeNameFr>
          <EventTypeName>Sponsor’s speech</EventTypeName>
          <PersonId>31098</PersonId>
          <PersonOfficialFirstName>Sukh</PersonOfficialFirstName>
          <PersonOfficialLastName>Dhaliwal</PersonOfficialLastName>
          <PersonMiddleName>
          </PersonMiddleName>
          <PersonName>Sukh Dhaliwal</PersonName>
          <SenateSystemAffiliationId />
          <CaucusShortNameEn>Liberal</CaucusShortNameEn>
          <CaucusShortNameFr>Libéral</CaucusShortNameFr>
          <CaucusShortName>Liberal</CaucusShortName>
          <ParliamentNumber>45</ParliamentNumber>
          <SessionNumber>1</SessionNumber>
          <MeetingNumber>47</MeetingNumber>
          <SpeechDateTime>2025-10-30T17:31:24</SpeechDateTime>
          <UrlEn>
          </UrlEn>
          <UrlFr>
          </UrlFr>
          <Url>
          </Url>
        </Speeches>
        <Speeches>
          <BillId>0</BillId>
          <ChamberOrganizationId>1</ChamberOrganizationId>
          <InterventionEventId>13214272</InterventionEventId>
          <EventTypeId>60153</EventTypeId>
          <EventTypeNameEn>Response speech</EventTypeNameEn>
          <EventTypeNameFr>Discours en réponse</EventTypeNameFr>
          <EventTypeName>Response speech</EventTypeName>
          <PersonId>3306</PersonId>
          <PersonOfficialFirstName>Dan</PersonOfficialFirstName>
          <PersonOfficialLastName>Mazier</PersonOfficialLastName>
          <PersonMiddleName>
          </PersonMiddleName>
          <PersonName>Dan Mazier</PersonName>
          <SenateSystemAffiliationId />
          <CaucusShortNameEn>Conservative</CaucusShortNameEn>
          <CaucusShortNameFr>Conservateur</CaucusShortNameFr>
          <CaucusShortName>Conservative</CaucusShortName>
          <ParliamentNumber>45</ParliamentNumber>
          <SessionNumber>1</SessionNumber>
          <MeetingNumber>47</MeetingNumber>
          <SpeechDateTime>2025-10-30T17:49:48</SpeechDateTime>
          <UrlEn>
          </UrlEn>
          <UrlFr>
          </UrlFr>
          <Url>
          </Url>
        </Speeches>
        <Speeches>
          <BillId>0</BillId>
          <ChamberOrganizationId>1</ChamberOrganizationId>
          <InterventionEventId>13214291</InterventionEventId>
          <EventTypeId>60153</EventTypeId>
          <EventTypeNameEn>Response speech</EventTypeNameEn>
          <EventTypeNameFr>Discours en réponse</EventTypeNameFr>
          <EventTypeName>Response speech</EventTypeName>
          <PersonId>88552</PersonId>
          <PersonOfficialFirstName>Luc</PersonOfficialFirstName>
          <PersonOfficialLastName>Thériault</PersonOfficialLastName>
          <PersonMiddleName>
          </PersonMiddleName>
          <PersonName>Luc Thériault</PersonName>
          <SenateSystemAffiliationId />
          <CaucusShortNameEn>Bloc Québécois</CaucusShortNameEn>
          <CaucusShortNameFr>Bloc Québécois</CaucusShortNameFr>
          <CaucusShortName>Bloc Québécois</CaucusShortName>
          <ParliamentNumber>45</ParliamentNumber>
          <SessionNumber>1</SessionNumber>
          <MeetingNumber>47</MeetingNumber>
          <SpeechDateTime>2025-10-30T17:59:42</SpeechDateTime>
          <UrlEn>
          </UrlEn>
          <UrlFr>
          </UrlFr>
          <Url>
          </Url>
        </Speeches>
        <ContainsReferralToCommitteeEvent>false</ContainsReferralToCommitteeEvent>
        <ContainsRecommittalOfBillEvent>false</ContainsRecommittalOfBillEvent>
      </HouseBillStages>
      <HouseBillStages>
        <BillStageId>60049</BillStageId>
        <BillStageNameEn>Consideration in committee</BillStageNameEn>
        <BillStageNameFr>Examen en comité</BillStageNameFr>
        <BillStageName>Consideration in committee</BillStageName>
        <ChamberOrganizationId>0</ChamberOrganizationId>
        <ParliamentNumber>0</ParliamentNumber>
        <SessionNumber>0</SessionNumber>
        <State>1</State>
        <StateNameEn>Not reached</StateNameEn>
        <StateNameFr>Non atteint</StateNameFr>
        <StateAsOfDate />
        <StateName>Not reached</StateName>
        <Committee />
        <EndOfStageEvent />
        <StageEventCount>0</StageEventCount>
        <LastStageEventStartDateTime />
        <Speeches />
        <ContainsReferralToCommitteeEvent>false</ContainsReferralToCommitteeEvent>
        <ContainsRecommittalOfBillEvent>false</ContainsRecommittalOfBillEvent>
      </HouseBillStages>
      <HouseBillStages>
        <BillStageId>60032</BillStageId>
        <BillStageNameEn>Report stage</BillStageNameEn>
        <BillStageNameFr>Étape du rapport</BillStageNameFr>
        <BillStageName>Report stage</BillStageName>
        <ChamberOrganizationId>0</ChamberOrganizationId>
        <ParliamentNumber>0</ParliamentNumber>
        <SessionNumber>0</SessionNumber>
        <State>1</State>
        <StateNameEn>Not reached</StateNameEn>
        <StateNameFr>Non atteinte</StateNameFr>
        <StateAsOfDate />
        <StateName>Not reached</StateName>
        <Committee />
        <EndOfStageEvent />
        <StageEventCount>0</StageEventCount>
        <LastStageEventStartDateTime />
        <Speeches />
        <ContainsReferralToCommitteeEvent>false</ContainsReferralToCommitteeEvent>
        <ContainsRecommittalOfBillEvent>false</ContainsRecommittalOfBillEvent>
      </HouseBillStages>
      <HouseBillStages>
        <BillStageId>60031</BillStageId>
        <BillStageNameEn>Third reading</BillStageNameEn>
        <BillStageNameFr>Troisième lecture</BillStageNameFr>
        <BillStageName>Third reading</BillStageName>
        <ChamberOrganizationId>0</ChamberOrganizationId>
        <ParliamentNumber>0</ParliamentNumber>
        <SessionNumber>0</SessionNumber>
        <State>1</State>
        <StateNameEn>Not reached</StateNameEn>
        <StateNameFr>Non atteinte</StateNameFr>
        <StateAsOfDate />
        <StateName>Not reached</StateName>
        <Committee />
        <EndOfStageEvent />
        <StageEventCount>0</StageEventCount>
        <LastStageEventStartDateTime />
        <Speeches />
        <ContainsReferralToCommitteeEvent>false</ContainsReferralToCommitteeEvent>
        <ContainsRecommittalOfBillEvent>false</ContainsRecommittalOfBillEvent>
      </HouseBillStages>
      <SenateBillStages>
        <BillStageId>60029</BillStageId>
        <BillStageNameEn>First reading</BillStageNameEn>
        <BillStageNameFr>Première lecture</BillStageNameFr>
        <BillStageName>First reading</BillStageName>
        <ChamberOrganizationId>0</ChamberOrganizationId>
        <ParliamentNumber>0</ParliamentNumber>
        <SessionNumber>0</SessionNumber>
        <State>1</State>
        <StateNameEn>Not reached</StateNameEn>
        <StateNameFr>Non atteinte</StateNameFr>
        <StateAsOfDate />
        <StateName>Not reached</StateName>
        <Committee />
        <EndOfStageEvent />
        <StageEventCount>0</StageEventCount>
        <LastStageEventStartDateTime />
        <Speeches />
        <ContainsReferralToCommitteeEvent>false</ContainsReferralToCommitteeEvent>
        <ContainsRecommittalOfBillEvent>false</ContainsRecommittalOfBillEvent>
      </SenateBillStages>
      <SenateBillStages>
        <BillStageId>60030</BillStageId>
        <BillStageNameEn>Second reading</BillStageNameEn>
        <BillStageNameFr>Deuxième lecture</BillStageNameFr>
        <BillStageName>Second reading</BillStageName>
        <ChamberOrganizationId>0</ChamberOrganizationId>
        <ParliamentNumber>0</ParliamentNumber>
        <SessionNumber>0</SessionNumber>
        <State>1</State>
        <StateNameEn>Not reached</StateNameEn>
        <StateNameFr>Non atteinte</StateNameFr>
        <StateAsOfDate />
        <StateName>Not reached</StateName>
        <Committee />
        <EndOfStageEvent />
        <StageEventCount>0</StageEventCount>
        <LastStageEventStartDateTime />
        <Speeches />
        <ContainsReferralToCommitteeEvent>false</ContainsReferralToCommitteeEvent>
        <ContainsRecommittalOfBillEvent>false</ContainsRecommittalOfBillEvent>
      </SenateBillStages>
      <SenateBillStages>
        <BillStageId>60031</BillStageId>
        <BillStageNameEn>Third reading</BillStageNameEn>
        <BillStageNameFr>Troisième lecture</BillStageNameFr>
        <BillStageName>Third reading</BillStageName>
        <ChamberOrganizationId>0</ChamberOrganizationId>
        <ParliamentNumber>0</ParliamentNumber>
        <SessionNumber>0</SessionNumber>
        <State>1</State>
        <StateNameEn>Not reached</StateNameEn>
        <StateNameFr>Non atteinte</StateNameFr>
        <StateAsOfDate />
        <StateName>Not reached</StateName>
        <Committee />
        <EndOfStageEvent />
        <StageEventCount>0</StageEventCount>
        <LastStageEventStartDateTime />
        <Speeches />
        <ContainsReferralToCommitteeEvent>false</ContainsReferralToCommitteeEvent>
        <ContainsRecommittalOfBillEvent>false</ContainsRecommittalOfBillEvent>
      </SenateBillStages>
    </BillStages>
    <Publications>
      <PublicationId>13599527</PublicationId>
      <PublicationTypeId>80701</PublicationTypeId>
      <PublicationTypeNameEn>First Reading</PublicationTypeNameEn>
      <PublicationTypeNameFr>Première lecture</PublicationTypeNameFr>
      <PublicationTypeName>First Reading</PublicationTypeName>
    </Publications>
    <WebReferences>
      <BillDocumentId>0</BillDocumentId>
      <TitleEn>Butler, M. et al. “The Federal Role in Health and Health Care”, In Brief, Library of Parliament, revised on 20 September 2013.</TitleEn>
      <TitleFr>Butler M. et al. « Le rôle fédéral dans le domaine de la santé et des soins de santé », En bref, Bibliothèque du Parlement, révisé le 20 septembre 2013.</TitleFr>
      <Title>Butler, M. et al. “The Federal Role in Health and Health Care”, In Brief, Library of Parliament, revised on 20 September 2013.</Title>
      <WebReferenceTypeId>8</WebReferenceTypeId>
      <WebReferenceTypeNameEn>Related Links</WebReferenceTypeNameEn>
      <WebReferenceTypeNameFr>Liens connexes</WebReferenceTypeNameFr>
      <WebReferenceTypeName>Related Links</WebReferenceTypeName>
      <UrlEn>https://lop.parl.ca/sites/PublicWebsite/default/en_CA/ResearchPublications/201191E</UrlEn>
      <UrlFr>https://lop.parl.ca/sites/PublicWebsite/default/fr_CA/ResearchPublications/201191E</UrlFr>
      <Url>https://lop.parl.ca/sites/PublicWebsite/default/en_CA/ResearchPublications/201191E</Url>
    </WebReferences>
    <WebReferences>
      <BillDocumentId>0</BillDocumentId>
      <TitleEn>Health Canada. Canada Health Act Annual Report 2023-2024, 13 June 2025.</TitleEn>
      <TitleFr>Santé Canada. Loi canadienne sur la santé : Rapport annuel 2023-2024, 13 juin 2025.</TitleFr>
      <Title>Health Canada. Canada Health Act Annual Report 2023-2024, 13 June 2025.</Title>
      <WebReferenceTypeId>8</WebReferenceTypeId>
      <WebReferenceTypeNameEn>Related Links</WebReferenceTypeNameEn>
      <WebReferenceTypeNameFr>Liens connexes</WebReferenceTypeNameFr>
      <WebReferenceTypeName>Related Links</WebReferenceTypeName>
      <UrlEn>https://www.canada.ca/en/health-canada/services/publications/health-system-services/canada-health-act-annual-report-2023-2024.html</UrlEn>
      <UrlFr>https://www.canada.ca/fr/sante-canada/services/publications/systeme-et-services-sante/loi-canadienne-sante-rapport-annuel-2023-2024.html</UrlFr>
      <Url>https://www.canada.ca/en/health-canada/services/publications/health-system-services/canada-health-act-annual-report-2023-2024.html</Url>
    </WebReferences>
    <WebReferences>
      <BillDocumentId>0</BillDocumentId>
      <TitleEn>Association of Faculties of Medicine of Canada. “Health Services in Canada”, Chapter 12 in AFMC Primer on Population Health, ed. I. McDowell et al., 2016.</TitleEn>
      <TitleFr>Association des facultés de médecine du Canada. « L’organisation des services de santé au Canada », Chapitre 12 dans AFMC Notions de santé des populations, ed. I. McDowell et al., 2016.</TitleFr>
      <Title>Association of Faculties of Medicine of Canada. “Health Services in Canada”, Chapter 12 in AFMC Primer on Population Health, ed. I. McDowell et al., 2016.</Title>
      <WebReferenceTypeId>8</WebReferenceTypeId>
      <WebReferenceTypeNameEn>Related Links</WebReferenceTypeNameEn>
      <WebReferenceTypeNameFr>Liens connexes</WebReferenceTypeNameFr>
      <WebReferenceTypeName>Related Links</WebReferenceTypeName>
      <UrlEn>https://phprimer.afmc.ca/en/part-iii/chapter-12/</UrlEn>
      <UrlFr>https://phprimer.afmc.ca/fr/partie-iii/chapitre-12/</UrlFr>
      <Url>https://phprimer.afmc.ca/en/part-iii/chapter-12/</Url>
    </WebReferences>
    <SenatePreStudyCommitteeDetails />
    <SimilarBills />
    <IsDroppedFromSenateOrderPaper>false</IsDroppedFromSenateOrderPaper>
    <IsSessionOngoing>true</IsSessionOngoing>
  </Bill>
</Bills>